mlm_form/__init__.py
mlm_form/__main__.py
mlm_form/app.py
mlm_form/templates.py
mlm_form/validation.py
mlm_form-0.1.0.dist-info/METADATA
mlm_form-0.1.0.dist-info/WHEEL
mlm_form-0.1.0.dist-info/entry_points.txt
mlm_form-0.1.0.dist-info/RECORD
